ccres_disdrometer_processing/__init__.py
ccres_disdrometer_processing/compute_dz_time_series.py
ccres_disdrometer_processing/constants.py
ccres_disdrometer_processing/create_input_files_quicklooks.py
ccres_disdrometer_processing/dz_1event_degrade.py
ccres_disdrometer_processing/dz_1event_from_good_preprocessed_file.py
ccres_disdrometer_processing/logger.py
ccres_disdrometer_processing/metadata.py
ccres_disdrometer_processing/open_disdro_netcdf.py
ccres_disdrometer_processing/open_radar_netcdf.py
ccres_disdrometer_processing/open_weather_netcdf.py
ccres_disdrometer_processing/quicklooks_1event.py
ccres_disdrometer_processing/rain_event_selection.py
ccres_disdrometer_processing/scattering.py
ccres_disdrometer_processing/utils.py
ccres_disdrometer_processing/assets/__init__.py
ccres_disdrometer_processing/assets/logo/__init__.py
ccres_disdrometer_processing/cli/cli.py
ccres_disdrometer_processing/cli/preprocess_cli.py
ccres_disdrometer_processing/plot/__init__.py
ccres_disdrometer_processing/plot/plot.py
ccres_disdrometer_processing/plot/utils.py
ccres_disdrometer_processing/plot/colormap/dcr_cmap.py
ccres_disdrometer_processing/processing/extract_data_for_dynamic_plots.py
ccres_disdrometer_processing/processing/plot_per_event.py
ccres_disdrometer_processing/processing/preprocessed_file2processed.py
ccres_disdrometer_processing/processing/preprocessed_file2processed_noweather.py
ccres_disdrometer_processing/processing/preprocessed_file2processed_weather.py
ccres_disdrometer_processing/processing/template_monitoring_timeseries_pdf.py
ccres_disdrometer_processing-0.3.4.dist-info/licenses/LICENSE
ccres_disdrometer_processing-0.3.4.dist-info/METADATA
ccres_disdrometer_processing-0.3.4.dist-info/WHEEL
ccres_disdrometer_processing-0.3.4.dist-info/entry_points.txt
ccres_disdrometer_processing-0.3.4.dist-info/top_level.txt
ccres_disdrometer_processing-0.3.4.dist-info/RECORD
