Metadata-Version: 2.4
Name: ccres_disdrometer_processing
Version: 0.3.4
Summary: CCRES code to convert data
Author-email: ACTRIS-CCRES <ccres-dev@listes.ipsl.fr>
License:                     GNU AFFERO GENERAL PUBLIC LICENSE
Project-URL: homepage, https://github.com/ACTRIS-CCRES/ccres_disdrometer_processing
Project-URL: documentation, https://ccres-disdrometer-processing.readthedocs.io/en/latest/?version=latest
Project-URL: repository, https://github.com/ACTRIS-CCRES/ccres_disdrometer_processing
Project-URL: changelog, https://github.com/ACTRIS-CCRES/ccres_disdrometer_processing/blob/main/CHANGELOG.md
Project-URL: Bug Tracker, https://github.com/ACTRIS-CCRES/ccres_disdrometer_processing/issues
Keywords: ccres_disdrometer_processing
Classifier: Development Status :: 2 - Pre-Alpha
Classifier: Intended Audience :: Developers
Classifier: License :: OSI Approved :: GNU Affero General Public License v3
Classifier: Natural Language :: English
Classifier: Programming Language :: Python :: Implementation :: CPython
Classifier: Programming Language :: Python :: 3
Classifier: Programming Language :: Python :: 3.9
Classifier: Programming Language :: Python :: 3.10
Classifier: Programming Language :: Python :: 3.11
Requires-Python: >=3.9
License-File: LICENSE
Requires-Dist: click
Requires-Dist: netCDF4
Requires-Dist: xarray
Requires-Dist: pandas
Requires-Dist: numpy<2
Requires-Dist: requests
Requires-Dist: matplotlib
Requires-Dist: scipy
Requires-Dist: pyarrow
Requires-Dist: pytmatrix==0.3.2
Requires-Dist: toml
Provides-Extra: dev
Requires-Dist: ccres_disdrometer_processing; extra == "dev"
Requires-Dist: pytest>=6.1.1; extra == "dev"
Requires-Dist: pytest-cov>=2.10.1; extra == "dev"
Requires-Dist: pytest-mock>=3.6.1; extra == "dev"
Requires-Dist: coverage>=5.3; extra == "dev"
Requires-Dist: requests; extra == "dev"
Requires-Dist: tox; extra == "dev"
Requires-Dist: pre-commit; extra == "dev"
Requires-Dist: bump2version; extra == "dev"
Requires-Dist: ruff; extra == "dev"
Requires-Dist: mypy; extra == "dev"
Provides-Extra: docs
Requires-Dist: ablog; extra == "docs"
Requires-Dist: numpydoc; extra == "docs"
Requires-Dist: myst-nb; extra == "docs"
Requires-Dist: sphinx; extra == "docs"
Requires-Dist: sphinx-autobuild; extra == "docs"
Requires-Dist: sphinx-book-theme; extra == "docs"
Requires-Dist: sphinx-design; extra == "docs"
Requires-Dist: sphinx-examples; extra == "docs"
Requires-Dist: sphinx-copybutton; extra == "docs"
Requires-Dist: sphinx-serve; extra == "docs"
Requires-Dist: sphinx-tabs; extra == "docs"
Requires-Dist: sphinx-togglebutton; extra == "docs"
Requires-Dist: sphinx-thebe; extra == "docs"
Requires-Dist: sphinxcontrib-bibtex; extra == "docs"
Requires-Dist: sphinxcontrib-youtube; extra == "docs"
Requires-Dist: sphinxext-opengraph; extra == "docs"
Dynamic: license-file
